photinia/__init__.py
photinia/att.py
photinia/conf.py
photinia/init.py
photinia/reg.py
photinia/train.py
photinia/apps/__init__.py
photinia/apps/ram.py
photinia/apps/deep_rl/__init__.py
photinia/apps/deep_rl/actors_critics.py
photinia/apps/deep_rl/common.py
photinia/apps/deep_rl/ddpg.py
photinia/apps/imagenet/__init__.py
photinia/apps/imagenet/alexnet.py
photinia/apps/imagenet/vgg.py
photinia/apps/pix2pix/__init__.py
photinia/apps/pix2pix/unet.py
photinia/cnn/__init__.py
photinia/cnn/common.py
photinia/cnn/dcae.py
photinia/cnn/vgg16.py
photinia/cnn/vgg19.py
photinia/core/__init__.py
photinia/core/application.py
photinia/core/basic.py
photinia/core/common.py
photinia/core/convolutional.py
photinia/core/embedding.py
photinia/core/misc.py
photinia/core/recurrent.py
photinia/dnn/__init__.py
photinia/dnn/mlp.py
photinia/dnn/resnet.py
photinia/io/__init__.py
photinia/io/data.py
photinia/io/dumpers.py
photinia/misc/__init__.py
photinia/ops/__init__.py
photinia/ops/common.py
photinia/ops/losses.py
photinia/rnn/__init__.py
photinia/rnn/bptt.py
photinia/rnn/seqae.py
photinia/rnn/seqpae.py
photinia/testing/__init__.py
photinia/testing/winton.py
photinia/testing/xi.py
photinia/testing/zhkun.py
photinia/utils/__init__.py
photinia/utils/common.py
photinia/utils/image.py
photinia/utils/seq.py
photinia-0.6.2.20190619.dist-info/DESCRIPTION.rst
photinia-0.6.2.20190619.dist-info/METADATA
photinia-0.6.2.20190619.dist-info/RECORD
photinia-0.6.2.20190619.dist-info/WHEEL
photinia-0.6.2.20190619.dist-info/metadata.json
photinia-0.6.2.20190619.dist-info/top_level.txt
photinia-0.6.2.20190619.dist-info/zip-safe
