Metadata-Version: 2.0
Name: photinia
Version: 0.6.2.20190619
Summary: Build deep learning models quickly for scientists in an object-oriented way.
Home-page: https://github.com/XoriieInpottn/photinia
Author: darklab_502
Author-email: gylv@mail.ustc.edu.cn
License: Free
Keywords: deep learning,neural network
Platform: any
Classifier: Programming Language :: Python :: 3.6
Classifier: Programming Language :: Python :: 3.7
Requires-Dist: numpy
Requires-Dist: scipy
Requires-Dist: pymongo
Requires-Dist: opencv-python
Requires-Dist: prettytable
